remarking/__init__.py
remarking/__main__.py
remarking/cli/__init__.py
remarking/cli/app.py
remarking/cli/cli.py
remarking/cli/commands/__init__.py
remarking/cli/commands/csv_writer_command.py
remarking/cli/commands/json_writer_command.py
remarking/cli/commands/table_writer_command.py
remarking/cli/common.py
remarking/cli/extract.py
remarking/cli/list.py
remarking/cli/log.py
remarking/cli/writer.py
remarking/cli/writer_command.py
remarking/cli/writer_command_runner.py
remarking/highlight_extractor/highlight_extractor.py
remarking/highlight_extractor/remarkable_highlight_extractor.py
remarking/models.py
remarking/rmcloud.py
remarking/storage/sqlalchemy_storage.py
remarking/storage/storage.py
remarking-0.1.4.dist-info/entry_points.txt
remarking-0.1.4.dist-info/LICENSE
remarking-0.1.4.dist-info/WHEEL
remarking-0.1.4.dist-info/METADATA
remarking-0.1.4.dist-info/RECORD
