Metadata-Version: 2.1
Name: remarking
Version: 0.1.4
Summary: Extract highlights from your ReMarkable tablet.
Home-page: https://remarking.readthedocs.io/en/latest/
License: GPL-3.0-only
Keywords: highlight,remarkable-tablet,extract,annotate workflow
Author: sabidib
Author-email: samy@sabidib.com
Requires-Python: >=3.7,<4.0
Classifier: Development Status :: 4 - Beta
Classifier: Environment :: Console
Classifier: License :: OSI Approved :: GNU General Public License v3 (GPLv3)
Classifier: Operating System :: OS Independent
Classifier: Programming Language :: Python :: 3
Classifier: Programming Language :: Python :: 3.7
Classifier: Programming Language :: Python :: 3.8
Classifier: Programming Language :: Python :: 3.9
Provides-Extra: docs
Requires-Dist: SQLAlchemy (>=1.4.20,<2.0.0)
Requires-Dist: Sphinx (>=4.1.1,<5.0.0); extra == "docs"
Requires-Dist: click (>=8.0.1,<9.0.0)
Requires-Dist: click-help-colors (>=0.9.1,<0.10.0)
Requires-Dist: furo (>=2021.7.5-beta.38,<2022.0.0); extra == "docs"
Requires-Dist: halo (>=0.0.31,<0.0.32)
Requires-Dist: python-dateutil (>=2.8.1,<3.0.0)
Requires-Dist: rmapy (>=0.3.1,<0.4.0)
Requires-Dist: tabulate (>=0.8.9,<0.9.0)
Project-URL: Documentation, https://remarking.readthedocs.io/en/latest/
Project-URL: Repository, https://www.github.com/sabidib/remarking
